odoo10_addon_stay-10.0.1.0.0.99.dev27-py3.8-nspkg.pth
odoo/addons/stay/README.rst
odoo/addons/stay/__init__.py
odoo/addons/stay/__manifest__.py
odoo/addons/stay/base_config_settings.py
odoo/addons/stay/base_config_settings_view.xml
odoo/addons/stay/company.py
odoo/addons/stay/partner.py
odoo/addons/stay/partner_view.xml
odoo/addons/stay/report.xml
odoo/addons/stay/stay.py
odoo/addons/stay/stay_data.xml
odoo/addons/stay/stay_demo.xml
odoo/addons/stay/stay_view.xml
odoo/addons/stay/data/cron.xml
odoo/addons/stay/data/mail_template.xml
odoo/addons/stay/i18n/fr.po
odoo/addons/stay/i18n/zh_CN.po
odoo/addons/stay/report/report_stay_journal.xml
odoo/addons/stay/security/ir.model.access.csv
odoo/addons/stay/security/stay_security.xml
odoo/addons/stay/static/description/icon.png
odoo/addons/stay/tests/__init__.py
odoo/addons/stay/tests/test_generate_journal.py
odoo/addons/stay/wizard/__init__.py
odoo/addons/stay/wizard/stay_journal_generate.py
odoo/addons/stay/wizard/stay_journal_generate_view.xml
odoo/addons/stay/wizard/stay_journal_print.py
odoo/addons/stay/wizard/stay_journal_print_view.xml
odoo/addons/stay/wizard/stay_stay_xlsx.py
odoo/addons/stay/wizard/stay_stay_xlsx_view.xml
odoo10_addon_stay-10.0.1.0.0.99.dev27.dist-info/METADATA
odoo10_addon_stay-10.0.1.0.0.99.dev27.dist-info/WHEEL
odoo10_addon_stay-10.0.1.0.0.99.dev27.dist-info/namespace_packages.txt
odoo10_addon_stay-10.0.1.0.0.99.dev27.dist-info/top_level.txt
odoo10_addon_stay-10.0.1.0.0.99.dev27.dist-info/RECORD
