Metadata-Version: 2.1
Name: odoo10-addon-stay
Version: 10.0.1.0.0.99.dev27
Summary: Simple management of stays and meals
Home-page: http://www.barroux.org
Author: Barroux Abbey, Akretion, Odoo Community Association (OCA)
Author-email: support@odoo-community.org
License: AGPL-3
Platform: UNKNOWN
Classifier: Programming Language :: Python
Classifier: Framework :: Odoo
Classifier: Framework :: Odoo :: 10.0
Classifier: License :: OSI Approved :: GNU Affero General Public License v3
Requires-Python: ~=2.7
Requires-Dist: odoo10-addon-web-timeline
Requires-Dist: odoo (<10.1dev,>=10.0)
Requires-Dist: xlsxwriter
